canvy/__init__.py
canvy/const.py
canvy/main.py
canvy/types.py
canvy/utils.py
canvy/scripts/__init__.py
canvy/scripts/downloader.py
canvy/scripts/grades.py
canvy/scripts/tutor.py
canvy/tui/__init__.py
canvy/tui/const.py
canvy/tui/download.py
canvy/tui/help.py
canvy/tui/login.py
canvy/tui/main.py
canvy/tui/settings.py
canvy/tui/tui.py
canvy/tui/tutor.py
canvy-1.1.0.dist-info/METADATA
canvy-1.1.0.dist-info/WHEEL
canvy-1.1.0.dist-info/entry_points.txt
canvy-1.1.0.dist-info/RECORD
