Metadata-Version: 2.4
Name: canvy
Version: 1.1.0
Summary: Sync files from Canvas courses
Author-email: "James K." <jameskowal10@gmail.com>
License-Expression: MIT
Requires-Python: ==3.12.*
Requires-Dist: agno>=1.3.1
Requires-Dist: anthropic>=0.52.1
Requires-Dist: canvasapi>=3.3.0
Requires-Dist: duckduckgo-search>=8.0.1
Requires-Dist: hatch>=1.14.1
Requires-Dist: mcp>=1.7.1
Requires-Dist: ollama>=0.4.8
Requires-Dist: openai>=1.75.0
Requires-Dist: platformdirs>=4.3.7
Requires-Dist: pydantic>=2.11.3
Requires-Dist: pypdf>=5.4.0
Requires-Dist: pytest-cov>=6.1.1
Requires-Dist: pytest>=8.3.5
Requires-Dist: qdrant-client>=1.13.3
Requires-Dist: rich>=14.0.0
Requires-Dist: textual-dev>=1.7.0
Requires-Dist: textual>=3.1.1
Requires-Dist: toml>=0.10.2
Requires-Dist: typer>=0.15.2
Requires-Dist: typst>=0.13.2
